dealuz/__init__.py
dealuz/core.py
dealuz/definitions.py
dealuz-0.1.3.dist-info/licenses/LICENSE.txt
dealuz-0.1.3.dist-info/METADATA
dealuz-0.1.3.dist-info/WHEEL
dealuz-0.1.3.dist-info/top_level.txt
dealuz-0.1.3.dist-info/RECORD
