Metadata-Version: 2.4
Name: dealuz
Version: 0.1.3
Summary: a short and simple package implementing Data Envelopment Analysis (DEA)
Author-email: Andre da Luz <email.andredaluz@gmail.com>
License-Expression: MIT
Project-URL: Source, https://github.com/da-luz/dealuz/tree/main
Requires-Python: >=3.11.12
License-File: LICENSE.txt
Requires-Dist: numpy>=1.26.3
Requires-Dist: pandas>=2.1.4
Requires-Dist: PuLP==2.8.0
Requires-Dist: python-dateutil>=2.9.0.post0
Requires-Dist: pytz>=2025.2
Requires-Dist: six>=1.17.0
Requires-Dist: tzdata>=2025.2
Dynamic: license-file
